<sequence version="3.10"><step type="SMS_TaskSequence_SetVariableAction" name="README" description="" runIn="WinPEandFullOS" successCodeList="0" retryCount="0" runFromNet="false"><action>tsenv.exe "README=This task sequence demonstrates how to set the SMSTSSoftwareUpdateScanTimeout variable. For more information on task sequence variable see: https://docs.microsoft.com/en-us/mem/configmgr/osd/understand/task-sequence-variables" /hiddenflag:False</action><defaultVarList><variable name="DoNotShowVariableValue" property="DoNotShowVariableValue" hidden="true">false</variable><variable name="VariableName" property="VariableName" hidden="true">README</variable><variable name="VariableValue" property="VariableValue" hidden="true">This task sequence demonstrates how to set the SMSTSSoftwareUpdateScanTimeout variable. For more information on task sequence variable see: https://docs.microsoft.com/en-us/mem/configmgr/osd/understand/task-sequence-variables</variable></defaultVarList></step><step type="SMS_TaskSequence_SetVariableAction" name="Set SMSTSSoftwareUpdateScanTimeout to 30 minutes" description="Use a high value if you expect numerous updates during the scan. The default value is 3600 seconds (60 minutes)" runIn="WinPEandFullOS" successCodeList="0" retryCount="0" runFromNet="false"><action>tsenv.exe "SMSTSSoftwareUpdateScanTimeout=1800" /hiddenflag:False</action><defaultVarList><variable name="DoNotShowVariableValue" property="DoNotShowVariableValue" hidden="true">false</variable><variable name="VariableName" property="VariableName" hidden="true">SMSTSSoftwareUpdateScanTimeout</variable><variable name="VariableValue" property="VariableValue" hidden="true">1800</variable></defaultVarList></step></sequence>
